CHANGES.rst
CONTRIBUTORS.rst
DEVELOP.rst
LICENSE.GPL
LICENSE.rst
MANIFEST.in
README.rst
setup.cfg
setup.py
docs/index.rst
src/plone/__init__.py
src/plone.oidc.egg-info/PKG-INFO
src/plone.oidc.egg-info/SOURCES.txt
src/plone.oidc.egg-info/dependency_links.txt
src/plone.oidc.egg-info/entry_points.txt
src/plone.oidc.egg-info/namespace_packages.txt
src/plone.oidc.egg-info/not-zip-safe
src/plone.oidc.egg-info/requires.txt
src/plone.oidc.egg-info/top_level.txt
src/plone/oidc/__init__.py
src/plone/oidc/configure.zcml
src/plone/oidc/interfaces.py
src/plone/oidc/permissions.zcml
src/plone/oidc/setuphandlers.py
src/plone/oidc/testing.py
src/plone/oidc/upgrades.py
src/plone/oidc/upgrades.zcml
src/plone/oidc/utils.py
src/plone/oidc/browser/__init__.py
src/plone/oidc/browser/configure.zcml
src/plone/oidc/browser/overrides/.gitkeep
src/plone/oidc/browser/static/.gitkeep
src/plone/oidc/locales/plone.oidc.pot
src/plone/oidc/locales/update.sh
src/plone/oidc/membrane/__init__.py
src/plone/oidc/membrane/behaviors.py
src/plone/oidc/membrane/configure.zcml
src/plone/oidc/membrane/user.py
src/plone/oidc/profiles/default/browserlayer.xml
src/plone/oidc/profiles/default/catalog.xml
src/plone/oidc/profiles/default/metadata.xml
src/plone/oidc/profiles/default/registry.xml
src/plone/oidc/profiles/default/rolemap.xml
src/plone/oidc/profiles/default/workflows.xml
src/plone/oidc/profiles/default/workflows/oidc_membrane_user_workflow/definition.xml
src/plone/oidc/profiles/testing/types.xml
src/plone/oidc/profiles/testing/workflows.xml
src/plone/oidc/profiles/testing/types/OidcTestUser.xml
src/plone/oidc/profiles/uninstall/browserlayer.xml
src/plone/oidc/profiles/uninstall/workflows.xml
src/plone/oidc/tests/__init__.py
src/plone/oidc/tests/helpers.py
src/plone/oidc/tests/test_behaviors.py
src/plone/oidc/tests/test_robot.py
src/plone/oidc/tests/test_setup.py
src/plone/oidc/tests/test_workflows.py
src/plone/oidc/tests/robot/test_example.robot