Metadata-Version: 1.1
Name: plone.oidc
Version: 1.0.0a2
Summary: OpenID Connect implementation in Plone
Home-page: https://pypi.org/project/plone.oidc
Author: Md Nazrul Islam
Author-email: email2nazrul@gmail.com
License: GPL version 2
Keywords: Python Plone OpenID oAuth2
Platform: UNKNOWN
Classifier: Environment :: Web Environment
Classifier: Framework :: Plone
Classifier: Framework :: Plone :: 5.0
Classifier: Framework :: Plone :: 5.1
Classifier: Framework :: Plone :: 5.2
Classifier: Programming Language :: Python
Classifier: Programming Language :: Python :: 2.7
Classifier: Programming Language :: Python :: 3.4
Classifier: Programming Language :: Python :: 3.5
Classifier: Programming Language :: Python :: 3.6
Classifier: Programming Language :: Python :: 3.7
Classifier: Operating System :: OS Independent
Classifier: License :: OSI Approved :: GNU General Public License v2 (GPLv2)
